Metadata-Version: 2.1
Name: zanshin-sdk-python
Version: 1.6.4.1
Summary: Python SDK to access the Tenchi Security Zanshin API v1
Home-page: https://github.com/tenchi-security/zanshin-sdk-python
License: Apache Software License
Author: Tenchi Security
Author-email: contact@tenchisecurity.com
Requires-Python: >=3.9,<4.0
Classifier: Development Status :: 5 - Production/Stable
Classifier: Environment :: Other Environment
Classifier: Intended Audience :: Developers
Classifier: Intended Audience :: System Administrators
Classifier: License :: OSI Approved :: Apache Software License
Classifier: License :: Other/Proprietary License
Classifier: Natural Language :: English
Classifier: Operating System :: OS Independent
Classifier: Programming Language :: Python
Classifier: Programming Language :: Python :: 3
Classifier: Programming Language :: Python :: 3.9
Classifier: Programming Language :: Python :: 3.10
Classifier: Programming Language :: Python :: 3.11
Classifier: Programming Language :: Python :: 3.12
Classifier: Programming Language :: Python :: 3.13
Classifier: Topic :: Security
Classifier: Topic :: Software Development :: Libraries
Requires-Dist: boto3 (>=1.34.84,<2.0.0)
Requires-Dist: httpx (>=0.27.0,<0.28.0)
Requires-Dist: poetry-plugin-export (>=1.8.0,<2.0.0)
Requires-Dist: pydantic (>=2.7.1,<3.0.0)
Requires-Dist: urllib3 (>=1.26.20,<2.0.0)
